adb_utils/__init__.py
adb_utils/adb_utils.py
python_adb_utils-0.0.11.dist-info/METADATA
python_adb_utils-0.0.11.dist-info/RECORD
python_adb_utils-0.0.11.dist-info/WHEEL
python_adb_utils-0.0.11.dist-info/top_level.txt
