Metadata-Version: 2.1
Name: python-adb-utils
Version: 0.0.11
Summary: This is the first test of a ADB interface for Python
Home-page: https://github.com/christopherferreira3/Python-ADB-Tools
Author: Christopher Ferreira
Author-email: christopher.ferreira3@outlook.com
License: UNKNOWN
Platform: UNKNOWN
Classifier: Programming Language :: Python :: 3
Classifier: License :: OSI Approved :: MIT License
Classifier: Operating System :: OS Independent
